nhlang/__init__.py
nhlang/interpreter.py
nhlang-0.1.1.dist-info/METADATA
nhlang-0.1.1.dist-info/WHEEL
nhlang-0.1.1.dist-info/entry_points.txt
nhlang-0.1.1.dist-info/top_level.txt
nhlang-0.1.1.dist-info/RECORD
