Metadata-Version: 2.4
Name: nhlang
Version: 0.1.1
Summary: A simple interpreter for NH Language
Author-email: Huy <wuocwee@gmail.com>
License: MIT
Requires-Python: >=3.7
